{
  "info": {
    "name": "Adblock Compiler API",
    "description": "Auto-generated from docs/api/openapi.yaml. Run 'deno task postman:collection' to regenerate.\n\n**Compiler-as-a-Service** for adblock filter lists. Transform, optimize, and combine filter lists from multiple sources with real-time progress tracking.\n\n## Features\n- 🎯 Multi-Source Compilation\n- ⚡ Performance (Gzip compression, caching, request deduplication)\n- 🔄 Circuit Breaker with retry logic\n- 📊 Visual Diff between compilations\n- 📡 Real-time progress via SSE and WebSocket\n- 🎪 Batch Processing\n- 🌍 Universal (Deno, Node.js, Cloudflare Workers, browsers)\n\n## Links\n- [GitHub Repository](https://github.com/jaypatrick/adblock-compiler)\n- [Documentation](https://github.com/jaypatrick/adblock-compiler/tree/master/docs)\n- [Web UI](https://adblock-compiler.jayson-knight.workers.dev/)",
    "schema": "https://schema.getpostman.com/json/collection/v2.1.0/collection.json",
    "_postman_id": "adblock-compiler-api",
    "version": "2.0.0"
  },
  "variable": [
    {
      "key": "baseUrl",
      "value": "http://localhost:8787",
      "type": "string"
    },
    {
      "key": "prodUrl",
      "value": "https://adblock-compiler.jayson-knight.workers.dev",
      "type": "string"
    },
    {
      "key": "requestId",
      "value": "",
      "type": "string"
    },
    {
      "key": "adminKey",
      "value": "",
      "type": "string",
      "description": "Admin API key for protected admin endpoints (X-Admin-Key header)"
    },
    {
      "key": "userId",
      "value": "",
      "type": "string",
      "description": "User ID captured from Create User response"
    },
    {
      "key": "apiKeyPrefix",
      "value": "",
      "type": "string",
      "description": "API key prefix captured from Create API Key response"
    }
  ],
  "item": [
    {
      "name": "Compilation",
      "description": "Filter list compilation endpoints",
      "item": [
        {
          "name": "Compile filter list (JSON)",
          "description": "Compile filter lists and return results as JSON. Results are cached for 1 hour.",
          "event": [
            {
              "listen": "test",
              "script": {
                "type": "text/javascript",
                "exec": [
                  "pm.test('Status code is 200', function () {",
                  "    pm.response.to.have.status(200);",
                  "});",
                  "",
                  "pm.test('Response is JSON', function () {",
                  "    pm.response.to.be.json;",
                  "});"
                ]
              }
            }
          ],
          "request": {
            "method": "POST",
            "header": [
              {
                "key": "Content-Type",
                "value": "application/json",
                "type": "text"
              }
            ],
            "url": {
              "raw": "{{baseUrl}}/compile",
              "host": [
                "{{baseUrl}}"
              ],
              "path": [
                "compile"
              ]
            },
            "body": {
              "mode": "raw",
              "raw": "{\n    \"configuration\": {\n        \"name\": \"My Filter List\",\n        \"sources\": [\n            {\n                \"source\": \"https://example.com/filters.txt\",\n                \"transformations\": [\n                    \"RemoveComments\",\n                    \"Validate\"\n                ]\n            }\n        ],\n        \"transformations\": [\n            \"Deduplicate\"\n        ]\n    }\n}",
              "options": {
                "raw": {
                  "language": "json"
                }
              }
            },
            "description": "Compile filter lists and return results as JSON. Results are cached for 1 hour.\nSupports request deduplication for concurrent identical requests.\n"
          }
        },
        {
          "name": "Batch compile multiple lists",
          "description": "Compile multiple filter lists in parallel (max 10 per batch)",
          "event": [
            {
              "listen": "test",
              "script": {
                "type": "text/javascript",
                "exec": [
                  "pm.test('Status code is 200', function () {",
                  "    pm.response.to.have.status(200);",
                  "});",
                  "",
                  "pm.test('Response is JSON', function () {",
                  "    pm.response.to.be.json;",
                  "});"
                ]
              }
            }
          ],
          "request": {
            "method": "POST",
            "header": [
              {
                "key": "Content-Type",
                "value": "application/json",
                "type": "text"
              }
            ],
            "url": {
              "raw": "{{baseUrl}}/compile/batch",
              "host": [
                "{{baseUrl}}"
              ],
              "path": [
                "compile",
                "batch"
              ]
            },
            "body": {
              "mode": "raw",
              "raw": "{\n    \"requests\": [\n        {}\n    ]\n}",
              "options": {
                "raw": {
                  "language": "json"
                }
              }
            },
            "description": "Compile multiple filter lists in parallel (max 10 per batch)"
          }
        },
        {
          "name": "Parse filter rules into AST",
          "description": "Parses adblock filter rules into an Abstract Syntax Tree representation",
          "event": [
            {
              "listen": "test",
              "script": {
                "type": "text/javascript",
                "exec": [
                  "pm.test('Status code is 200', function () {",
                  "    pm.response.to.have.status(200);",
                  "});",
                  "",
                  "pm.test('Response is JSON', function () {",
                  "    pm.response.to.be.json;",
                  "});"
                ]
              }
            }
          ],
          "request": {
            "method": "POST",
            "header": [
              {
                "key": "Content-Type",
                "value": "application/json",
                "type": "text"
              }
            ],
            "url": {
              "raw": "{{baseUrl}}/ast/parse",
              "host": [
                "{{baseUrl}}"
              ],
              "path": [
                "ast",
                "parse"
              ]
            },
            "body": {
              "mode": "raw",
              "raw": "{\n    \"rules\": [\n        \"string\"\n    ],\n    \"text\": \"string\"\n}",
              "options": {
                "raw": {
                  "language": "json"
                }
              }
            },
            "description": "Parses adblock filter rules into an Abstract Syntax Tree representation"
          }
        }
      ]
    },
    {
      "name": "Streaming",
      "description": "Real-time event streaming endpoints",
      "item": [
        {
          "name": "Compile with real-time progress (SSE)",
          "description": "Compile filter lists with real-time progress updates via Server-Sent Events.",
          "event": [
            {
              "listen": "test",
              "script": {
                "type": "text/javascript",
                "exec": [
                  "pm.test('Status code is 200', function () {",
                  "    pm.response.to.have.status(200);",
                  "});",
                  "",
                  "pm.test('Response is SSE stream', function () {",
                  "    pm.expect(pm.response.headers.get('Content-Type')).to.include('text/event-stream');",
                  "});"
                ]
              }
            }
          ],
          "request": {
            "method": "POST",
            "header": [
              {
                "key": "Content-Type",
                "value": "application/json",
                "type": "text"
              }
            ],
            "url": {
              "raw": "{{baseUrl}}/compile/stream",
              "host": [
                "{{baseUrl}}"
              ],
              "path": [
                "compile",
                "stream"
              ]
            },
            "body": {
              "mode": "raw",
              "raw": "{\n    \"configuration\": {},\n    \"preFetchedContent\": {},\n    \"benchmark\": false,\n    \"turnstileToken\": \"string\",\n    \"priority\": \"standard\"\n}",
              "options": {
                "raw": {
                  "language": "json"
                }
              }
            },
            "description": "Compile filter lists with real-time progress updates via Server-Sent Events.\nStreams events including source downloads, transformations, diagnostics, cache operations, network events, and metrics.\n"
          }
        }
      ]
    },
    {
      "name": "Queue",
      "description": "Async job queue management",
      "item": [
        {
          "name": "Queue async compilation job",
          "description": "Queue a compilation job for asynchronous processing. Returns immediately with a request ID.",
          "event": [
            {
              "listen": "test",
              "script": {
                "type": "text/javascript",
                "exec": [
                  "pm.test('Status code is 202', function () {",
                  "    pm.response.to.have.status(202);",
                  "});",
                  "",
                  "pm.test('Response is JSON', function () {",
                  "    pm.response.to.be.json;",
                  "});"
                ]
              }
            }
          ],
          "request": {
            "method": "POST",
            "header": [
              {
                "key": "Content-Type",
                "value": "application/json",
                "type": "text"
              }
            ],
            "url": {
              "raw": "{{baseUrl}}/compile/async",
              "host": [
                "{{baseUrl}}"
              ],
              "path": [
                "compile",
                "async"
              ]
            },
            "body": {
              "mode": "raw",
              "raw": "{\n    \"configuration\": {},\n    \"preFetchedContent\": {},\n    \"benchmark\": false,\n    \"turnstileToken\": \"string\",\n    \"priority\": \"standard\"\n}",
              "options": {
                "raw": {
                  "language": "json"
                }
              }
            },
            "description": "Queue a compilation job for asynchronous processing. Returns immediately with a request ID.\nUse GET /queue/results/{requestId} to retrieve results when complete.\n"
          }
        },
        {
          "name": "Queue batch async compilation",
          "description": "Queue multiple compilations for async processing",
          "event": [
            {
              "listen": "test",
              "script": {
                "type": "text/javascript",
                "exec": [
                  "pm.test('Status code is 202', function () {",
                  "    pm.response.to.have.status(202);",
                  "});",
                  "",
                  "pm.test('Response is JSON', function () {",
                  "    pm.response.to.be.json;",
                  "});"
                ]
              }
            }
          ],
          "request": {
            "method": "POST",
            "header": [
              {
                "key": "Content-Type",
                "value": "application/json",
                "type": "text"
              }
            ],
            "url": {
              "raw": "{{baseUrl}}/compile/batch/async",
              "host": [
                "{{baseUrl}}"
              ],
              "path": [
                "compile",
                "batch",
                "async"
              ]
            },
            "body": {
              "mode": "raw",
              "raw": "{\n    \"requests\": [\n        {}\n    ]\n}",
              "options": {
                "raw": {
                  "language": "json"
                }
              }
            },
            "description": "Queue multiple compilations for async processing"
          }
        },
        {
          "name": "Get queue statistics",
          "description": "Returns queue health metrics and job statistics",
          "event": [
            {
              "listen": "test",
              "script": {
                "type": "text/javascript",
                "exec": [
                  "pm.test('Status code is 200', function () {",
                  "    pm.response.to.have.status(200);",
                  "});",
                  "",
                  "pm.test('Response is JSON', function () {",
                  "    pm.response.to.be.json;",
                  "});"
                ]
              }
            }
          ],
          "request": {
            "method": "GET",
            "header": [],
            "url": {
              "raw": "{{baseUrl}}/queue/stats",
              "host": [
                "{{baseUrl}}"
              ],
              "path": [
                "queue",
                "stats"
              ]
            },
            "description": "Returns queue health metrics and job statistics"
          }
        },
        {
          "name": "Get async job results",
          "description": "Retrieve results for a completed async compilation job",
          "event": [
            {
              "listen": "test",
              "script": {
                "type": "text/javascript",
                "exec": [
                  "pm.test('Status code is 200', function () {",
                  "    pm.response.to.have.status(200);",
                  "});",
                  "",
                  "pm.test('Response is JSON', function () {",
                  "    pm.response.to.be.json;",
                  "});"
                ]
              }
            }
          ],
          "request": {
            "method": "GET",
            "header": [],
            "url": {
              "raw": "{{baseUrl}}/queue/results/:requestId",
              "host": [
                "{{baseUrl}}"
              ],
              "path": [
                "queue",
                "results",
                ":requestId"
              ],
              "variable": [
                {
                  "key": "requestId",
                  "value": "{{requestId}}",
                  "description": "Path parameter: requestId"
                }
              ]
            },
            "description": "Retrieve results for a completed async compilation job"
          }
        },
        {
          "name": "Get queue job history",
          "description": "Returns job history and queue depth over time",
          "event": [
            {
              "listen": "test",
              "script": {
                "type": "text/javascript",
                "exec": [
                  "pm.test('Status code is 200', function () {",
                  "    pm.response.to.have.status(200);",
                  "});",
                  "",
                  "pm.test('Response is JSON', function () {",
                  "    pm.response.to.be.json;",
                  "});"
                ]
              }
            }
          ],
          "request": {
            "method": "GET",
            "header": [],
            "url": {
              "raw": "{{baseUrl}}/queue/history",
              "host": [
                "{{baseUrl}}"
              ],
              "path": [
                "queue",
                "history"
              ]
            },
            "description": "Returns job history and queue depth over time"
          }
        },
        {
          "name": "Cancel a queued job",
          "description": "Marks a pending queue job as cancelled",
          "event": [
            {
              "listen": "test",
              "script": {
                "type": "text/javascript",
                "exec": [
                  "pm.test('Status code is 200', function () {",
                  "    pm.response.to.have.status(200);",
                  "});",
                  "",
                  "pm.test('Response is JSON', function () {",
                  "    pm.response.to.be.json;",
                  "});"
                ]
              }
            }
          ],
          "request": {
            "method": "POST",
            "header": [],
            "url": {
              "raw": "{{baseUrl}}/queue/cancel/:requestId",
              "host": [
                "{{baseUrl}}"
              ],
              "path": [
                "queue",
                "cancel",
                ":requestId"
              ],
              "variable": [
                {
                  "key": "requestId",
                  "value": "{{requestId}}",
                  "description": "Path parameter: requestId"
                }
              ]
            },
            "description": "Marks a pending queue job as cancelled"
          }
        }
      ]
    },
    {
      "name": "Metrics",
      "description": "Performance metrics and statistics",
      "item": [
        {
          "name": "Get API information",
          "description": "Returns API version, available endpoints, and usage examples",
          "event": [
            {
              "listen": "test",
              "script": {
                "type": "text/javascript",
                "exec": [
                  "pm.test('Status code is 200', function () {",
                  "    pm.response.to.have.status(200);",
                  "});",
                  "",
                  "pm.test('Response is JSON', function () {",
                  "    pm.response.to.be.json;",
                  "});"
                ]
              }
            }
          ],
          "request": {
            "method": "GET",
            "header": [],
            "url": {
              "raw": "{{baseUrl}}/api",
              "host": [
                "{{baseUrl}}"
              ],
              "path": [
                "api"
              ]
            },
            "description": "Returns API version, available endpoints, and usage examples"
          }
        },
        {
          "name": "Get performance metrics",
          "description": "Returns aggregated metrics for the last 30 minutes",
          "event": [
            {
              "listen": "test",
              "script": {
                "type": "text/javascript",
                "exec": [
                  "pm.test('Status code is 200', function () {",
                  "    pm.response.to.have.status(200);",
                  "});",
                  "",
                  "pm.test('Response is JSON', function () {",
                  "    pm.response.to.be.json;",
                  "});"
                ]
              }
            }
          ],
          "request": {
            "method": "GET",
            "header": [],
            "url": {
              "raw": "{{baseUrl}}/metrics",
              "host": [
                "{{baseUrl}}"
              ],
              "path": [
                "metrics"
              ]
            },
            "description": "Returns aggregated metrics for the last 30 minutes"
          }
        },
        {
          "name": "Get latest deployment version",
          "description": "Returns the current version from deployment history",
          "event": [
            {
              "listen": "test",
              "script": {
                "type": "text/javascript",
                "exec": [
                  "pm.test('Status code is 200', function () {",
                  "    pm.response.to.have.status(200);",
                  "});",
                  "",
                  "pm.test('Response is JSON', function () {",
                  "    pm.response.to.be.json;",
                  "});"
                ]
              }
            }
          ],
          "request": {
            "method": "GET",
            "header": [],
            "url": {
              "raw": "{{baseUrl}}/api/version",
              "host": [
                "{{baseUrl}}"
              ],
              "path": [
                "api",
                "version"
              ]
            },
            "description": "Returns the current version from deployment history"
          }
        },
        {
          "name": "Get deployment history",
          "description": "Returns deployment history records",
          "event": [
            {
              "listen": "test",
              "script": {
                "type": "text/javascript",
                "exec": [
                  "pm.test('Status code is 200', function () {",
                  "    pm.response.to.have.status(200);",
                  "});",
                  "",
                  "pm.test('Response is JSON', function () {",
                  "    pm.response.to.be.json;",
                  "});"
                ]
              }
            }
          ],
          "request": {
            "method": "GET",
            "header": [],
            "url": {
              "raw": "{{baseUrl}}/api/deployments",
              "host": [
                "{{baseUrl}}"
              ],
              "path": [
                "api",
                "deployments"
              ],
              "query": [
                {
                  "key": "limit",
                  "value": "{{limit}}",
                  "description": "Maximum number of records to return",
                  "disabled": true
                },
                {
                  "key": "version",
                  "value": "{{version}}",
                  "description": "Filter by version",
                  "disabled": true
                },
                {
                  "key": "status",
                  "value": "{{status}}",
                  "description": "Filter by deployment status",
                  "disabled": true
                },
                {
                  "key": "branch",
                  "value": "{{branch}}",
                  "description": "Filter by branch name",
                  "disabled": true
                }
              ]
            },
            "description": "Returns deployment history records"
          }
        },
        {
          "name": "Get deployment statistics",
          "description": "Returns aggregated deployment statistics",
          "event": [
            {
              "listen": "test",
              "script": {
                "type": "text/javascript",
                "exec": [
                  "pm.test('Status code is 200', function () {",
                  "    pm.response.to.have.status(200);",
                  "});",
                  "",
                  "pm.test('Response is JSON', function () {",
                  "    pm.response.to.be.json;",
                  "});"
                ]
              }
            }
          ],
          "request": {
            "method": "GET",
            "header": [],
            "url": {
              "raw": "{{baseUrl}}/api/deployments/stats",
              "host": [
                "{{baseUrl}}"
              ],
              "path": [
                "api",
                "deployments",
                "stats"
              ]
            },
            "description": "Returns aggregated deployment statistics"
          }
        },
        {
          "name": "Get Turnstile configuration",
          "description": "Returns the Cloudflare Turnstile site key and whether it is enabled",
          "event": [
            {
              "listen": "test",
              "script": {
                "type": "text/javascript",
                "exec": [
                  "pm.test('Status code is 200', function () {",
                  "    pm.response.to.have.status(200);",
                  "});",
                  "",
                  "pm.test('Response is JSON', function () {",
                  "    pm.response.to.be.json;",
                  "});"
                ]
              }
            }
          ],
          "request": {
            "method": "GET",
            "header": [],
            "url": {
              "raw": "{{baseUrl}}/api/turnstile-config",
              "host": [
                "{{baseUrl}}"
              ],
              "path": [
                "api",
                "turnstile-config"
              ]
            },
            "description": "Returns the Cloudflare Turnstile site key and whether it is enabled"
          }
        }
      ]
    },
    {
      "name": "WebSocket",
      "description": "Bidirectional real-time communication",
      "item": [
        {
          "name": "WebSocket endpoint for real-time compilation",
          "description": "Bidirectional WebSocket connection for real-time compilation with event streaming.",
          "event": [
            {
              "listen": "test",
              "script": {
                "type": "text/javascript",
                "exec": [
                  "pm.test('Status code is 200', function () {",
                  "    pm.response.to.have.status(200);",
                  "});"
                ]
              }
            }
          ],
          "request": {
            "method": "GET",
            "header": [],
            "url": {
              "raw": "{{baseUrl}}/ws/compile",
              "host": [
                "{{baseUrl}}"
              ],
              "path": [
                "ws",
                "compile"
              ]
            },
            "description": "Bidirectional WebSocket connection for real-time compilation with event streaming.\n\n**Client → Server Messages:**\n- `compile` - Start compilation\n- `cancel` - Cancel running compilation\n- `ping` - Heartbeat ping\n\n**Server → Client Messages:**\n- `welcome` - Connection established\n- `pong` - Heartbeat response\n- `compile:started` - Compilation started\n- `event` - Compilation event (source, transformation, progress, diagnostic, cache, network, metric)\n- `compile:complete` - Compilation finished successfully\n- `compile:error` - Compilation failed\n- `compile:cancelled` - Compilation cancelled\n- `error` - Error message\n\n**Features:**\n- Up to 3 concurrent compilations per connection\n- Automatic heartbeat (30s interval)\n- Connection timeout (5 minutes idle)\n- Session-based compilation tracking\n- Cancellation support\n"
          }
        }
      ]
    },
    {
      "name": "Admin",
      "description": "Administration endpoints for storage, auth, migration, and backends (require X-Admin-Key header)",
      "item": [
        {
          "name": "Get storage statistics",
          "description": "Returns database table counts and expired entry counts",
          "event": [
            {
              "listen": "test",
              "script": {
                "type": "text/javascript",
                "exec": [
                  "pm.test('Status code is 200', function () {",
                  "    pm.response.to.have.status(200);",
                  "});",
                  "",
                  "pm.test('Response is JSON', function () {",
                  "    pm.response.to.be.json;",
                  "});"
                ]
              }
            }
          ],
          "request": {
            "method": "GET",
            "header": [
              {
                "key": "X-Admin-Key",
                "value": "{{adminKey}}",
                "type": "text",
                "description": "Admin API key"
              }
            ],
            "url": {
              "raw": "{{baseUrl}}/admin/storage/stats",
              "host": [
                "{{baseUrl}}"
              ],
              "path": [
                "admin",
                "storage",
                "stats"
              ]
            },
            "description": "Returns database table counts and expired entry counts"
          }
        },
        {
          "name": "Clear expired entries",
          "description": "Deletes all expired entries from storage tables",
          "event": [
            {
              "listen": "test",
              "script": {
                "type": "text/javascript",
                "exec": [
                  "pm.test('Status code is 200', function () {",
                  "    pm.response.to.have.status(200);",
                  "});",
                  "",
                  "pm.test('Response is JSON', function () {",
                  "    pm.response.to.be.json;",
                  "});"
                ]
              }
            }
          ],
          "request": {
            "method": "POST",
            "header": [
              {
                "key": "X-Admin-Key",
                "value": "{{adminKey}}",
                "type": "text",
                "description": "Admin API key"
              }
            ],
            "url": {
              "raw": "{{baseUrl}}/admin/storage/clear-expired",
              "host": [
                "{{baseUrl}}"
              ],
              "path": [
                "admin",
                "storage",
                "clear-expired"
              ]
            },
            "description": "Deletes all expired entries from storage tables"
          }
        },
        {
          "name": "Clear cache entries",
          "description": "Deletes all cache entries from storage tables",
          "event": [
            {
              "listen": "test",
              "script": {
                "type": "text/javascript",
                "exec": [
                  "pm.test('Status code is 200', function () {",
                  "    pm.response.to.have.status(200);",
                  "});",
                  "",
                  "pm.test('Response is JSON', function () {",
                  "    pm.response.to.be.json;",
                  "});"
                ]
              }
            }
          ],
          "request": {
            "method": "POST",
            "header": [
              {
                "key": "X-Admin-Key",
                "value": "{{adminKey}}",
                "type": "text",
                "description": "Admin API key"
              }
            ],
            "url": {
              "raw": "{{baseUrl}}/admin/storage/clear-cache",
              "host": [
                "{{baseUrl}}"
              ],
              "path": [
                "admin",
                "storage",
                "clear-cache"
              ]
            },
            "description": "Deletes all cache entries from storage tables"
          }
        },
        {
          "name": "Export storage data",
          "description": "Exports storage entries as JSON (includes storage entries, filter cache, and compilation metadata; returned amounts subject to implementation limits)",
          "event": [
            {
              "listen": "test",
              "script": {
                "type": "text/javascript",
                "exec": [
                  "pm.test('Status code is 200', function () {",
                  "    pm.response.to.have.status(200);",
                  "});",
                  "",
                  "pm.test('Response is JSON', function () {",
                  "    pm.response.to.be.json;",
                  "});"
                ]
              }
            }
          ],
          "request": {
            "method": "GET",
            "header": [
              {
                "key": "X-Admin-Key",
                "value": "{{adminKey}}",
                "type": "text",
                "description": "Admin API key"
              }
            ],
            "url": {
              "raw": "{{baseUrl}}/admin/storage/export",
              "host": [
                "{{baseUrl}}"
              ],
              "path": [
                "admin",
                "storage",
                "export"
              ]
            },
            "description": "Exports storage entries as JSON (includes storage entries, filter cache, and compilation metadata; returned amounts subject to implementation limits)"
          }
        },
        {
          "name": "Vacuum database",
          "description": "Runs VACUUM on the D1 database to reclaim space",
          "event": [
            {
              "listen": "test",
              "script": {
                "type": "text/javascript",
                "exec": [
                  "pm.test('Status code is 200', function () {",
                  "    pm.response.to.have.status(200);",
                  "});",
                  "",
                  "pm.test('Response is JSON', function () {",
                  "    pm.response.to.be.json;",
                  "});"
                ]
              }
            }
          ],
          "request": {
            "method": "POST",
            "header": [
              {
                "key": "X-Admin-Key",
                "value": "{{adminKey}}",
                "type": "text",
                "description": "Admin API key"
              }
            ],
            "url": {
              "raw": "{{baseUrl}}/admin/storage/vacuum",
              "host": [
                "{{baseUrl}}"
              ],
              "path": [
                "admin",
                "storage",
                "vacuum"
              ]
            },
            "description": "Runs VACUUM on the D1 database to reclaim space"
          }
        },
        {
          "name": "List database tables",
          "description": "Returns all tables and indexes in the D1 database",
          "event": [
            {
              "listen": "test",
              "script": {
                "type": "text/javascript",
                "exec": [
                  "pm.test('Status code is 200', function () {",
                  "    pm.response.to.have.status(200);",
                  "});",
                  "",
                  "pm.test('Response is JSON', function () {",
                  "    pm.response.to.be.json;",
                  "});"
                ]
              }
            }
          ],
          "request": {
            "method": "GET",
            "header": [
              {
                "key": "X-Admin-Key",
                "value": "{{adminKey}}",
                "type": "text",
                "description": "Admin API key"
              }
            ],
            "url": {
              "raw": "{{baseUrl}}/admin/storage/tables",
              "host": [
                "{{baseUrl}}"
              ],
              "path": [
                "admin",
                "storage",
                "tables"
              ]
            },
            "description": "Returns all tables and indexes in the D1 database"
          }
        },
        {
          "name": "Execute read-only SQL query",
          "description": "Executes a SELECT-only SQL query against the D1 database for debugging",
          "event": [
            {
              "listen": "test",
              "script": {
                "type": "text/javascript",
                "exec": [
                  "pm.test('Status code is 200', function () {",
                  "    pm.response.to.have.status(200);",
                  "});",
                  "",
                  "pm.test('Response is JSON', function () {",
                  "    pm.response.to.be.json;",
                  "});"
                ]
              }
            }
          ],
          "request": {
            "method": "POST",
            "header": [
              {
                "key": "Content-Type",
                "value": "application/json",
                "type": "text"
              },
              {
                "key": "X-Admin-Key",
                "value": "{{adminKey}}",
                "type": "text",
                "description": "Admin API key"
              }
            ],
            "url": {
              "raw": "{{baseUrl}}/admin/storage/query",
              "host": [
                "{{baseUrl}}"
              ],
              "path": [
                "admin",
                "storage",
                "query"
              ]
            },
            "body": {
              "mode": "raw",
              "raw": "{\n    \"sql\": \"string\"\n}",
              "options": {
                "raw": {
                  "language": "json"
                }
              }
            },
            "description": "Executes a SELECT-only SQL query against the D1 database for debugging"
          }
        },
        {
          "name": "Create user",
          "description": "Creates a new user account. Requires Hyperdrive (PostgreSQL) binding.",
          "event": [
            {
              "listen": "test",
              "script": {
                "type": "text/javascript",
                "exec": [
                  "pm.test('Status code is 201', function () {",
                  "    pm.response.to.have.status(201);",
                  "});",
                  "",
                  "pm.test('Response is JSON', function () {",
                  "    pm.response.to.be.json;",
                  "});"
                ]
              }
            }
          ],
          "request": {
            "method": "POST",
            "header": [
              {
                "key": "Content-Type",
                "value": "application/json",
                "type": "text"
              },
              {
                "key": "X-Admin-Key",
                "value": "{{adminKey}}",
                "type": "text",
                "description": "Admin API key"
              }
            ],
            "url": {
              "raw": "{{baseUrl}}/admin/auth/users",
              "host": [
                "{{baseUrl}}"
              ],
              "path": [
                "admin",
                "auth",
                "users"
              ]
            },
            "body": {
              "mode": "raw",
              "raw": "{\n    \"email\": \"string\",\n    \"displayName\": \"string\",\n    \"role\": \"admin\"\n}",
              "options": {
                "raw": {
                  "language": "json"
                }
              }
            },
            "description": "Creates a new user account. Requires Hyperdrive (PostgreSQL) binding."
          }
        },
        {
          "name": "List API keys",
          "description": "Lists API keys for a user (without key hashes). Requires Hyperdrive (PostgreSQL) binding.",
          "event": [
            {
              "listen": "test",
              "script": {
                "type": "text/javascript",
                "exec": [
                  "pm.test('Status code is 200', function () {",
                  "    pm.response.to.have.status(200);",
                  "});",
                  "",
                  "pm.test('Response is JSON', function () {",
                  "    pm.response.to.be.json;",
                  "});"
                ]
              }
            }
          ],
          "request": {
            "method": "GET",
            "header": [
              {
                "key": "X-Admin-Key",
                "value": "{{adminKey}}",
                "type": "text",
                "description": "Admin API key"
              }
            ],
            "url": {
              "raw": "{{baseUrl}}/admin/auth/api-keys?userId={{userId}}",
              "host": [
                "{{baseUrl}}"
              ],
              "path": [
                "admin",
                "auth",
                "api-keys"
              ],
              "query": [
                {
                  "key": "userId",
                  "value": "{{userId}}",
                  "description": "User ID to list API keys for"
                }
              ]
            },
            "description": "Lists API keys for a user (without key hashes). Requires Hyperdrive (PostgreSQL) binding."
          }
        },
        {
          "name": "Create API key",
          "description": "Creates a new API key for a user. Requires Hyperdrive (PostgreSQL) binding.",
          "event": [
            {
              "listen": "test",
              "script": {
                "type": "text/javascript",
                "exec": [
                  "pm.test('Status code is 201', function () {",
                  "    pm.response.to.have.status(201);",
                  "});",
                  "",
                  "pm.test('Response is JSON', function () {",
                  "    pm.response.to.be.json;",
                  "});"
                ]
              }
            }
          ],
          "request": {
            "method": "POST",
            "header": [
              {
                "key": "Content-Type",
                "value": "application/json",
                "type": "text"
              },
              {
                "key": "X-Admin-Key",
                "value": "{{adminKey}}",
                "type": "text",
                "description": "Admin API key"
              }
            ],
            "url": {
              "raw": "{{baseUrl}}/admin/auth/api-keys",
              "host": [
                "{{baseUrl}}"
              ],
              "path": [
                "admin",
                "auth",
                "api-keys"
              ]
            },
            "body": {
              "mode": "raw",
              "raw": "{\n    \"userId\": \"string\",\n    \"name\": \"string\",\n    \"scopes\": [\n        \"string\"\n    ],\n    \"rateLimitPerMinute\": 0,\n    \"expiresAt\": \"string\"\n}",
              "options": {
                "raw": {
                  "language": "json"
                }
              }
            },
            "description": "Creates a new API key for a user. Requires Hyperdrive (PostgreSQL) binding.\n\n**Important:** The raw API key is only returned once. Store it securely.\n"
          }
        },
        {
          "name": "Revoke API key",
          "description": "Revokes an API key by ID or key prefix. Requires Hyperdrive (PostgreSQL) binding.",
          "event": [
            {
              "listen": "test",
              "script": {
                "type": "text/javascript",
                "exec": [
                  "pm.test('Status code is 200', function () {",
                  "    pm.response.to.have.status(200);",
                  "});",
                  "",
                  "pm.test('Response is JSON', function () {",
                  "    pm.response.to.be.json;",
                  "});"
                ]
              }
            }
          ],
          "request": {
            "method": "POST",
            "header": [
              {
                "key": "Content-Type",
                "value": "application/json",
                "type": "text"
              },
              {
                "key": "X-Admin-Key",
                "value": "{{adminKey}}",
                "type": "text",
                "description": "Admin API key"
              }
            ],
            "url": {
              "raw": "{{baseUrl}}/admin/auth/api-keys/revoke",
              "host": [
                "{{baseUrl}}"
              ],
              "path": [
                "admin",
                "auth",
                "api-keys",
                "revoke"
              ]
            },
            "body": {
              "mode": "raw",
              "raw": "{\n    \"apiKeyId\": \"string\",\n    \"keyPrefix\": \"string\"\n}",
              "options": {
                "raw": {
                  "language": "json"
                }
              }
            },
            "description": "Revokes an API key by ID or key prefix. Requires Hyperdrive (PostgreSQL) binding."
          }
        },
        {
          "name": "Validate API key",
          "description": "Validates an API key without authenticating a full request. Useful for the admin UI to test keys.",
          "event": [
            {
              "listen": "test",
              "script": {
                "type": "text/javascript",
                "exec": [
                  "pm.test('Status code is 200', function () {",
                  "    pm.response.to.have.status(200);",
                  "});",
                  "",
                  "pm.test('Response is JSON', function () {",
                  "    pm.response.to.be.json;",
                  "});"
                ]
              }
            }
          ],
          "request": {
            "method": "POST",
            "header": [
              {
                "key": "Content-Type",
                "value": "application/json",
                "type": "text"
              },
              {
                "key": "X-Admin-Key",
                "value": "{{adminKey}}",
                "type": "text",
                "description": "Admin API key"
              }
            ],
            "url": {
              "raw": "{{baseUrl}}/admin/auth/api-keys/validate",
              "host": [
                "{{baseUrl}}"
              ],
              "path": [
                "admin",
                "auth",
                "api-keys",
                "validate"
              ]
            },
            "body": {
              "mode": "raw",
              "raw": "{\n    \"apiKey\": \"string\"\n}",
              "options": {
                "raw": {
                  "language": "json"
                }
              }
            },
            "description": "Validates an API key without authenticating a full request. Useful for the admin UI to test keys."
          }
        },
        {
          "name": "Migrate D1 data to PostgreSQL",
          "description": "One-time migration that reads data from Cloudflare D1 (SQLite) and writes it to PostgreSQL via Hyperdrive.",
          "event": [
            {
              "listen": "test",
              "script": {
                "type": "text/javascript",
                "exec": [
                  "pm.test('Status code is 200', function () {",
                  "    pm.response.to.have.status(200);",
                  "});",
                  "",
                  "pm.test('Response is JSON', function () {",
                  "    pm.response.to.be.json;",
                  "});"
                ]
              }
            }
          ],
          "request": {
            "method": "POST",
            "header": [
              {
                "key": "X-Admin-Key",
                "value": "{{adminKey}}",
                "type": "text",
                "description": "Admin API key"
              }
            ],
            "url": {
              "raw": "{{baseUrl}}/admin/migrate/d1-to-pg",
              "host": [
                "{{baseUrl}}"
              ],
              "path": [
                "admin",
                "migrate",
                "d1-to-pg"
              ],
              "query": [
                {
                  "key": "dryRun",
                  "value": "{{dryRun}}",
                  "description": "Count rows without writing (dry run)",
                  "disabled": true
                },
                {
                  "key": "tables",
                  "value": "{{tables}}",
                  "description": "Comma-separated list of tables to migrate (default: all)",
                  "disabled": true
                }
              ]
            },
            "description": "One-time migration that reads data from Cloudflare D1 (SQLite) and writes it to PostgreSQL via Hyperdrive.\n\nMigrates the following tables: `storage_entries`, `filter_cache`, `compilation_metadata`.\n\nThe migration is:\n- **Idempotent**: uses ON CONFLICT DO NOTHING to skip existing rows\n- **Batched**: processes rows in chunks of 100\n- **Read-only on D1**: never modifies the source database\n- **Resumable**: can be re-run safely if interrupted\n"
          }
        },
        {
          "name": "Backend health status",
          "description": "Returns health and connectivity status of both D1 and PostgreSQL backends",
          "event": [
            {
              "listen": "test",
              "script": {
                "type": "text/javascript",
                "exec": [
                  "pm.test('Status code is 200', function () {",
                  "    pm.response.to.have.status(200);",
                  "});",
                  "",
                  "pm.test('Response is JSON', function () {",
                  "    pm.response.to.be.json;",
                  "});"
                ]
              }
            }
          ],
          "request": {
            "method": "GET",
            "header": [
              {
                "key": "X-Admin-Key",
                "value": "{{adminKey}}",
                "type": "text",
                "description": "Admin API key"
              }
            ],
            "url": {
              "raw": "{{baseUrl}}/admin/backends",
              "host": [
                "{{baseUrl}}"
              ],
              "path": [
                "admin",
                "backends"
              ]
            },
            "description": "Returns health and connectivity status of both D1 and PostgreSQL backends"
          }
        },
        {
          "name": "PostgreSQL storage statistics",
          "description": "Returns storage statistics from the PostgreSQL backend (mirrors /admin/storage/stats for D1)",
          "event": [
            {
              "listen": "test",
              "script": {
                "type": "text/javascript",
                "exec": [
                  "pm.test('Status code is 200', function () {",
                  "    pm.response.to.have.status(200);",
                  "});",
                  "",
                  "pm.test('Response is JSON', function () {",
                  "    pm.response.to.be.json;",
                  "});"
                ]
              }
            }
          ],
          "request": {
            "method": "GET",
            "header": [
              {
                "key": "X-Admin-Key",
                "value": "{{adminKey}}",
                "type": "text",
                "description": "Admin API key"
              }
            ],
            "url": {
              "raw": "{{baseUrl}}/admin/pg/stats",
              "host": [
                "{{baseUrl}}"
              ],
              "path": [
                "admin",
                "pg",
                "stats"
              ]
            },
            "description": "Returns storage statistics from the PostgreSQL backend (mirrors /admin/storage/stats for D1)"
          }
        },
        {
          "name": "Export PostgreSQL data",
          "description": "Exports data from the PostgreSQL backend (mirrors /admin/storage/export for D1)",
          "event": [
            {
              "listen": "test",
              "script": {
                "type": "text/javascript",
                "exec": [
                  "pm.test('Status code is 200', function () {",
                  "    pm.response.to.have.status(200);",
                  "});",
                  "",
                  "pm.test('Response is JSON', function () {",
                  "    pm.response.to.be.json;",
                  "});"
                ]
              }
            }
          ],
          "request": {
            "method": "GET",
            "header": [
              {
                "key": "X-Admin-Key",
                "value": "{{adminKey}}",
                "type": "text",
                "description": "Admin API key"
              }
            ],
            "url": {
              "raw": "{{baseUrl}}/admin/pg/export",
              "host": [
                "{{baseUrl}}"
              ],
              "path": [
                "admin",
                "pg",
                "export"
              ]
            },
            "description": "Exports data from the PostgreSQL backend (mirrors /admin/storage/export for D1)"
          }
        },
        {
          "name": "Clear expired PostgreSQL entries",
          "description": "Deletes all expired entries from PostgreSQL storage and cache tables",
          "event": [
            {
              "listen": "test",
              "script": {
                "type": "text/javascript",
                "exec": [
                  "pm.test('Status code is 200', function () {",
                  "    pm.response.to.have.status(200);",
                  "});",
                  "",
                  "pm.test('Response is JSON', function () {",
                  "    pm.response.to.be.json;",
                  "});"
                ]
              }
            }
          ],
          "request": {
            "method": "POST",
            "header": [
              {
                "key": "X-Admin-Key",
                "value": "{{adminKey}}",
                "type": "text",
                "description": "Admin API key"
              }
            ],
            "url": {
              "raw": "{{baseUrl}}/admin/pg/clear-expired",
              "host": [
                "{{baseUrl}}"
              ],
              "path": [
                "admin",
                "pg",
                "clear-expired"
              ]
            },
            "description": "Deletes all expired entries from PostgreSQL storage and cache tables"
          }
        },
        {
          "name": "Clear PostgreSQL cache",
          "description": "Deletes all cache entries from PostgreSQL tables",
          "event": [
            {
              "listen": "test",
              "script": {
                "type": "text/javascript",
                "exec": [
                  "pm.test('Status code is 200', function () {",
                  "    pm.response.to.have.status(200);",
                  "});",
                  "",
                  "pm.test('Response is JSON', function () {",
                  "    pm.response.to.be.json;",
                  "});"
                ]
              }
            }
          ],
          "request": {
            "method": "POST",
            "header": [
              {
                "key": "X-Admin-Key",
                "value": "{{adminKey}}",
                "type": "text",
                "description": "Admin API key"
              }
            ],
            "url": {
              "raw": "{{baseUrl}}/admin/pg/clear-cache",
              "host": [
                "{{baseUrl}}"
              ],
              "path": [
                "admin",
                "pg",
                "clear-cache"
              ]
            },
            "description": "Deletes all cache entries from PostgreSQL tables"
          }
        },
        {
          "name": "Execute read-only PostgreSQL query",
          "description": "Executes a SELECT-only SQL query against PostgreSQL for debugging (mirrors /admin/storage/query for D1)",
          "event": [
            {
              "listen": "test",
              "script": {
                "type": "text/javascript",
                "exec": [
                  "pm.test('Status code is 200', function () {",
                  "    pm.response.to.have.status(200);",
                  "});",
                  "",
                  "pm.test('Response is JSON', function () {",
                  "    pm.response.to.be.json;",
                  "});"
                ]
              }
            }
          ],
          "request": {
            "method": "POST",
            "header": [
              {
                "key": "Content-Type",
                "value": "application/json",
                "type": "text"
              },
              {
                "key": "X-Admin-Key",
                "value": "{{adminKey}}",
                "type": "text",
                "description": "Admin API key"
              }
            ],
            "url": {
              "raw": "{{baseUrl}}/admin/pg/query",
              "host": [
                "{{baseUrl}}"
              ],
              "path": [
                "admin",
                "pg",
                "query"
              ]
            },
            "body": {
              "mode": "raw",
              "raw": "{\n    \"sql\": \"string\"\n}",
              "options": {
                "raw": {
                  "language": "json"
                }
              }
            },
            "description": "Executes a SELECT-only SQL query against PostgreSQL for debugging (mirrors /admin/storage/query for D1)"
          }
        }
      ]
    },
    {
      "name": "Workflow",
      "description": "Durable execution workflow endpoints",
      "item": [
        {
          "name": "Start async compilation workflow",
          "description": "Creates a durable Cloudflare Workflow instance for compilation",
          "event": [
            {
              "listen": "test",
              "script": {
                "type": "text/javascript",
                "exec": [
                  "pm.test('Status code is 202', function () {",
                  "    pm.response.to.have.status(202);",
                  "});",
                  "",
                  "pm.test('Response is JSON', function () {",
                  "    pm.response.to.be.json;",
                  "});"
                ]
              }
            }
          ],
          "request": {
            "method": "POST",
            "header": [
              {
                "key": "Content-Type",
                "value": "application/json",
                "type": "text"
              }
            ],
            "url": {
              "raw": "{{baseUrl}}/workflow/compile",
              "host": [
                "{{baseUrl}}"
              ],
              "path": [
                "workflow",
                "compile"
              ]
            },
            "body": {
              "mode": "raw",
              "raw": "{\n    \"configuration\": {},\n    \"preFetchedContent\": {},\n    \"benchmark\": false,\n    \"turnstileToken\": \"string\",\n    \"priority\": \"standard\"\n}",
              "options": {
                "raw": {
                  "language": "json"
                }
              }
            },
            "description": "Creates a durable Cloudflare Workflow instance for compilation"
          }
        },
        {
          "name": "Start async batch compilation workflow",
          "description": "Creates a durable Cloudflare Workflow instance for batch compilation",
          "event": [
            {
              "listen": "test",
              "script": {
                "type": "text/javascript",
                "exec": [
                  "pm.test('Status code is 202', function () {",
                  "    pm.response.to.have.status(202);",
                  "});",
                  "",
                  "pm.test('Response is JSON', function () {",
                  "    pm.response.to.be.json;",
                  "});"
                ]
              }
            }
          ],
          "request": {
            "method": "POST",
            "header": [
              {
                "key": "Content-Type",
                "value": "application/json",
                "type": "text"
              }
            ],
            "url": {
              "raw": "{{baseUrl}}/workflow/batch",
              "host": [
                "{{baseUrl}}"
              ],
              "path": [
                "workflow",
                "batch"
              ]
            },
            "body": {
              "mode": "raw",
              "raw": "{\n    \"requests\": [\n        {}\n    ]\n}",
              "options": {
                "raw": {
                  "language": "json"
                }
              }
            },
            "description": "Creates a durable Cloudflare Workflow instance for batch compilation"
          }
        },
        {
          "name": "Start cache warming workflow",
          "description": "Triggers manual cache warming for specified configurations",
          "event": [
            {
              "listen": "test",
              "script": {
                "type": "text/javascript",
                "exec": [
                  "pm.test('Status code is 202', function () {",
                  "    pm.response.to.have.status(202);",
                  "});",
                  "",
                  "pm.test('Response is JSON', function () {",
                  "    pm.response.to.be.json;",
                  "});"
                ]
              }
            }
          ],
          "request": {
            "method": "POST",
            "header": [
              {
                "key": "Content-Type",
                "value": "application/json",
                "type": "text"
              }
            ],
            "url": {
              "raw": "{{baseUrl}}/workflow/cache-warm",
              "host": [
                "{{baseUrl}}"
              ],
              "path": [
                "workflow",
                "cache-warm"
              ]
            },
            "body": {
              "mode": "raw",
              "raw": "{\n    \"configurations\": [\n        {}\n    ]\n}",
              "options": {
                "raw": {
                  "language": "json"
                }
              }
            },
            "description": "Triggers manual cache warming for specified configurations"
          }
        },
        {
          "name": "Start health monitoring workflow",
          "description": "Triggers manual health check for specified filter list sources",
          "event": [
            {
              "listen": "test",
              "script": {
                "type": "text/javascript",
                "exec": [
                  "pm.test('Status code is 202', function () {",
                  "    pm.response.to.have.status(202);",
                  "});",
                  "",
                  "pm.test('Response is JSON', function () {",
                  "    pm.response.to.be.json;",
                  "});"
                ]
              }
            }
          ],
          "request": {
            "method": "POST",
            "header": [
              {
                "key": "Content-Type",
                "value": "application/json",
                "type": "text"
              }
            ],
            "url": {
              "raw": "{{baseUrl}}/workflow/health-check",
              "host": [
                "{{baseUrl}}"
              ],
              "path": [
                "workflow",
                "health-check"
              ]
            },
            "body": {
              "mode": "raw",
              "raw": "{\n    \"sources\": [\n        {}\n    ],\n    \"alertOnFailure\": false\n}",
              "options": {
                "raw": {
                  "language": "json"
                }
              }
            },
            "description": "Triggers manual health check for specified filter list sources"
          }
        },
        {
          "name": "Get workflow instance status",
          "description": "Returns the current status and output of a workflow instance",
          "event": [
            {
              "listen": "test",
              "script": {
                "type": "text/javascript",
                "exec": [
                  "pm.test('Status code is 200', function () {",
                  "    pm.response.to.have.status(200);",
                  "});",
                  "",
                  "pm.test('Response is JSON', function () {",
                  "    pm.response.to.be.json;",
                  "});"
                ]
              }
            }
          ],
          "request": {
            "method": "GET",
            "header": [],
            "url": {
              "raw": "{{baseUrl}}/workflow/status/:workflowType/:instanceId",
              "host": [
                "{{baseUrl}}"
              ],
              "path": [
                "workflow",
                "status",
                ":workflowType",
                ":instanceId"
              ],
              "variable": [
                {
                  "key": "workflowType",
                  "value": "{{workflowType}}",
                  "description": "Path parameter: workflowType"
                },
                {
                  "key": "instanceId",
                  "value": "{{instanceId}}",
                  "description": "Path parameter: instanceId"
                }
              ]
            },
            "description": "Returns the current status and output of a workflow instance"
          }
        },
        {
          "name": "Get workflow metrics",
          "description": "Returns aggregated metrics for all workflow types",
          "event": [
            {
              "listen": "test",
              "script": {
                "type": "text/javascript",
                "exec": [
                  "pm.test('Status code is 200', function () {",
                  "    pm.response.to.have.status(200);",
                  "});",
                  "",
                  "pm.test('Response is JSON', function () {",
                  "    pm.response.to.be.json;",
                  "});"
                ]
              }
            }
          ],
          "request": {
            "method": "GET",
            "header": [],
            "url": {
              "raw": "{{baseUrl}}/workflow/metrics",
              "host": [
                "{{baseUrl}}"
              ],
              "path": [
                "workflow",
                "metrics"
              ]
            },
            "description": "Returns aggregated metrics for all workflow types"
          }
        },
        {
          "name": "Get workflow events",
          "description": "Returns progress events for a specific workflow instance",
          "event": [
            {
              "listen": "test",
              "script": {
                "type": "text/javascript",
                "exec": [
                  "pm.test('Status code is 200', function () {",
                  "    pm.response.to.have.status(200);",
                  "});",
                  "",
                  "pm.test('Response is JSON', function () {",
                  "    pm.response.to.be.json;",
                  "});"
                ]
              }
            }
          ],
          "request": {
            "method": "GET",
            "header": [],
            "url": {
              "raw": "{{baseUrl}}/workflow/events/:workflowId",
              "host": [
                "{{baseUrl}}"
              ],
              "path": [
                "workflow",
                "events",
                ":workflowId"
              ],
              "variable": [
                {
                  "key": "workflowId",
                  "value": "{{workflowId}}",
                  "description": "Path parameter: workflowId"
                }
              ],
              "query": [
                {
                  "key": "since",
                  "value": "{{since}}",
                  "description": "Return only events after this timestamp",
                  "disabled": true
                }
              ]
            },
            "description": "Returns progress events for a specific workflow instance"
          }
        }
      ]
    },
    {
      "name": "Health",
      "description": "Health monitoring endpoints",
      "item": [
        {
          "name": "Get latest health check results",
          "description": "Returns the results of the most recent health monitoring workflow run",
          "event": [
            {
              "listen": "test",
              "script": {
                "type": "text/javascript",
                "exec": [
                  "pm.test('Status code is 200', function () {",
                  "    pm.response.to.have.status(200);",
                  "});",
                  "",
                  "pm.test('Response is JSON', function () {",
                  "    pm.response.to.be.json;",
                  "});"
                ]
              }
            }
          ],
          "request": {
            "method": "GET",
            "header": [],
            "url": {
              "raw": "{{baseUrl}}/health/latest",
              "host": [
                "{{baseUrl}}"
              ],
              "path": [
                "health",
                "latest"
              ]
            },
            "description": "Returns the results of the most recent health monitoring workflow run"
          }
        },
        {
          "name": "Basic health check",
          "description": "Returns current service health status and version",
          "event": [
            {
              "listen": "test",
              "script": {
                "type": "text/javascript",
                "exec": [
                  "pm.test('Status code is 200', function () {",
                  "    pm.response.to.have.status(200);",
                  "});",
                  "",
                  "pm.test('Response is JSON', function () {",
                  "    pm.response.to.be.json;",
                  "});"
                ]
              }
            }
          ],
          "request": {
            "method": "GET",
            "header": [],
            "url": {
              "raw": "{{baseUrl}}/health",
              "host": [
                "{{baseUrl}}"
              ],
              "path": [
                "health"
              ]
            },
            "description": "Returns current service health status and version"
          }
        }
      ]
    },
    {
      "name": "Browser Rendering",
      "description": "Endpoints backed by the Cloudflare Browser Rendering binding (`BROWSER`). Used for resolving redirect chains and monitoring filter-list source URLs for changes.",
      "item": [
        {
          "name": "Resolve canonical URL via browser",
          "description": "Navigates to a URL using the Cloudflare Browser Rendering binding and returns the",
          "event": [
            {
              "listen": "test",
              "script": {
                "type": "text/javascript",
                "exec": [
                  "pm.test('Status code is 200', function () {",
                  "    pm.response.to.have.status(200);",
                  "});",
                  "",
                  "pm.test('Response is JSON', function () {",
                  "    pm.response.to.be.json;",
                  "});"
                ]
              }
            }
          ],
          "request": {
            "method": "POST",
            "header": [
              {
                "key": "Content-Type",
                "value": "application/json",
                "type": "text"
              }
            ],
            "url": {
              "raw": "{{baseUrl}}/api/browser/resolve-url",
              "host": [
                "{{baseUrl}}"
              ],
              "path": [
                "api",
                "browser",
                "resolve-url"
              ]
            },
            "body": {
              "mode": "raw",
              "raw": "{\n    \"url\": \"https://example.com/redirect-me\",\n    \"waitUntil\": \"load\"\n}",
              "options": {
                "raw": {
                  "language": "json"
                }
              }
            },
            "description": "Navigates to a URL using the Cloudflare Browser Rendering binding and returns the\nfinal canonical URL after all redirects. Useful for discovering the true destination\nof redirect chains or URL shorteners before scheduling a filter-list download.\n\nRequires the `BROWSER` binding to be configured in `wrangler.toml`.\n"
          }
        },
        {
          "name": "Monitor filter-list sources for changes",
          "description": "Fetches each provided URL using the Cloudflare Browser Rendering binding and",
          "event": [
            {
              "listen": "test",
              "script": {
                "type": "text/javascript",
                "exec": [
                  "pm.test('Status code is 200', function () {",
                  "    pm.response.to.have.status(200);",
                  "});",
                  "",
                  "pm.test('Response is JSON', function () {",
                  "    pm.response.to.be.json;",
                  "});"
                ]
              }
            }
          ],
          "request": {
            "method": "POST",
            "header": [
              {
                "key": "Content-Type",
                "value": "application/json",
                "type": "text"
              }
            ],
            "url": {
              "raw": "{{baseUrl}}/api/browser/monitor",
              "host": [
                "{{baseUrl}}"
              ],
              "path": [
                "api",
                "browser",
                "monitor"
              ]
            },
            "body": {
              "mode": "raw",
              "raw": "{\n    \"urls\": [\n        \"https://example.com/filter-list.txt\",\n        \"https://another.example.com/rules.txt\"\n    ],\n    \"waitUntil\": \"load\"\n}",
              "options": {
                "raw": {
                  "language": "json"
                }
              }
            },
            "description": "Fetches each provided URL using the Cloudflare Browser Rendering binding and\ncomputes a content hash. The result is compared against the previously stored hash\n(if any) in `COMPILATION_CACHE` KV. Each source is reported as `changed` or\n`unchanged`. The latest result set is persisted under the KV key\n`browser:monitor:latest` and is retrievable via `GET /api/browser/monitor/latest`.\n\nRequires both the `BROWSER` and `COMPILATION_CACHE` bindings.\n"
          }
        },
        {
          "name": "Retrieve the latest monitor results",
          "description": "Returns the most recent result set written by `POST /api/browser/monitor`. Reads",
          "event": [
            {
              "listen": "test",
              "script": {
                "type": "text/javascript",
                "exec": [
                  "pm.test('Status code is 200', function () {",
                  "    pm.response.to.have.status(200);",
                  "});",
                  "",
                  "pm.test('Response is JSON', function () {",
                  "    pm.response.to.be.json;",
                  "});"
                ]
              }
            }
          ],
          "request": {
            "method": "GET",
            "header": [],
            "url": {
              "raw": "{{baseUrl}}/api/browser/monitor/latest",
              "host": [
                "{{baseUrl}}"
              ],
              "path": [
                "api",
                "browser",
                "monitor",
                "latest"
              ]
            },
            "description": "Returns the most recent result set written by `POST /api/browser/monitor`. Reads\nthe KV key `browser:monitor:latest` from `COMPILATION_CACHE`.\n\nRequires the `COMPILATION_CACHE` binding.\n"
          }
        }
      ]
    }
  ]
}
