{
  "scriptId": "425",
  "url": "file:///Users/jaysonknight/Projects/Code/adblock-compiler/src/transformations/DeduplicateTransformation.ts",
  "functions": [
    {
      "functionName": "",
      "ranges": [
        {
          "startOffset": 0,
          "endOffset": 2791,
          "count": 1
        }
      ],
      "isBlockCoverage": true
    },
    {
      "functionName": "<instance_members_initializer>",
      "ranges": [
        {
          "startOffset": 646,
          "endOffset": 756,
          "count": 15
        }
      ],
      "isBlockCoverage": true
    },
    {
      "functionName": "executeSync",
      "ranges": [
        {
          "startOffset": 934,
          "endOffset": 2788,
          "count": 0
        }
      ],
      "isBlockCoverage": false
    }
  ]
}