{
  "scriptId": "335",
  "url": "file:///Users/jaysonknight/Projects/Code/adblock-compiler/src/services/AnalyticsService.test.ts",
  "functions": [
    {
      "functionName": "",
      "ranges": [
        {
          "startOffset": 0,
          "endOffset": 11266,
          "count": 1
        }
      ],
      "isBlockCoverage": true
    },
    {
      "functionName": "<instance_members_initializer>",
      "ranges": [
        {
          "startOffset": 224,
          "endOffset": 239,
          "count": 23
        }
      ],
      "isBlockCoverage": true
    },
    {
      "functionName": "writeDataPoint",
      "ranges": [
        {
          "startOffset": 243,
          "endOffset": 328,
          "count": 23
        }
      ],
      "isBlockCoverage": true
    },
    {
      "functionName": "clear",
      "ranges": [
        {
          "startOffset": 331,
          "endOffset": 370,
          "count": 0
        }
      ],
      "isBlockCoverage": false
    },
    {
      "functionName": "",
      "ranges": [
        {
          "startOffset": 417,
          "endOffset": 988,
          "count": 1
        }
      ],
      "isBlockCoverage": true
    },
    {
      "functionName": "",
      "ranges": [
        {
          "startOffset": 500,
          "endOffset": 599,
          "count": 1
        }
      ],
      "isBlockCoverage": true
    },
    {
      "functionName": "",
      "ranges": [
        {
          "startOffset": 656,
          "endOffset": 809,
          "count": 1
        }
      ],
      "isBlockCoverage": true
    },
    {
      "functionName": "",
      "ranges": [
        {
          "startOffset": 876,
          "endOffset": 984,
          "count": 1
        }
      ],
      "isBlockCoverage": true
    },
    {
      "functionName": "",
      "ranges": [
        {
          "startOffset": 1033,
          "endOffset": 1418,
          "count": 1
        }
      ],
      "isBlockCoverage": true
    },
    {
      "functionName": "",
      "ranges": [
        {
          "startOffset": 1100,
          "endOffset": 1199,
          "count": 1
        }
      ],
      "isBlockCoverage": true
    },
    {
      "functionName": "",
      "ranges": [
        {
          "startOffset": 1261,
          "endOffset": 1414,
          "count": 1
        }
      ],
      "isBlockCoverage": true
    },
    {
      "functionName": "",
      "ranges": [
        {
          "startOffset": 1468,
          "endOffset": 3120,
          "count": 1
        }
      ],
      "isBlockCoverage": true
    },
    {
      "functionName": "",
      "ranges": [
        {
          "startOffset": 1536,
          "endOffset": 1834,
          "count": 1
        }
      ],
      "isBlockCoverage": true
    },
    {
      "functionName": "",
      "ranges": [
        {
          "startOffset": 1897,
          "endOffset": 2157,
          "count": 1
        }
      ],
      "isBlockCoverage": true
    },
    {
      "functionName": "",
      "ranges": [
        {
          "startOffset": 2213,
          "endOffset": 2749,
          "count": 1
        }
      ],
      "isBlockCoverage": true
    },
    {
      "functionName": "",
      "ranges": [
        {
          "startOffset": 2802,
          "endOffset": 3116,
          "count": 1
        }
      ],
      "isBlockCoverage": true
    },
    {
      "functionName": "writeDataPoint",
      "ranges": [
        {
          "startOffset": 2858,
          "endOffset": 2913,
          "count": 1
        }
      ],
      "isBlockCoverage": true
    },
    {
      "functionName": "",
      "ranges": [
        {
          "startOffset": 3179,
          "endOffset": 3805,
          "count": 1
        }
      ],
      "isBlockCoverage": true
    },
    {
      "functionName": "",
      "ranges": [
        {
          "startOffset": 3243,
          "endOffset": 3526,
          "count": 1
        }
      ],
      "isBlockCoverage": true
    },
    {
      "functionName": "",
      "ranges": [
        {
          "startOffset": 3578,
          "endOffset": 3801,
          "count": 1
        }
      ],
      "isBlockCoverage": true
    },
    {
      "functionName": "",
      "ranges": [
        {
          "startOffset": 3864,
          "endOffset": 4269,
          "count": 1
        }
      ],
      "isBlockCoverage": true
    },
    {
      "functionName": "",
      "ranges": [
        {
          "startOffset": 3928,
          "endOffset": 4265,
          "count": 1
        }
      ],
      "isBlockCoverage": true
    },
    {
      "functionName": "",
      "ranges": [
        {
          "startOffset": 4326,
          "endOffset": 4709,
          "count": 1
        }
      ],
      "isBlockCoverage": true
    },
    {
      "functionName": "",
      "ranges": [
        {
          "startOffset": 4388,
          "endOffset": 4705,
          "count": 1
        }
      ],
      "isBlockCoverage": true
    },
    {
      "functionName": "",
      "ranges": [
        {
          "startOffset": 4758,
          "endOffset": 5062,
          "count": 1
        }
      ],
      "isBlockCoverage": true
    },
    {
      "functionName": "",
      "ranges": [
        {
          "startOffset": 4812,
          "endOffset": 5058,
          "count": 1
        }
      ],
      "isBlockCoverage": true
    },
    {
      "functionName": "",
      "ranges": [
        {
          "startOffset": 5112,
          "endOffset": 5418,
          "count": 1
        }
      ],
      "isBlockCoverage": true
    },
    {
      "functionName": "",
      "ranges": [
        {
          "startOffset": 5167,
          "endOffset": 5414,
          "count": 1
        }
      ],
      "isBlockCoverage": true
    },
    {
      "functionName": "",
      "ranges": [
        {
          "startOffset": 5470,
          "endOffset": 5941,
          "count": 1
        }
      ],
      "isBlockCoverage": true
    },
    {
      "functionName": "",
      "ranges": [
        {
          "startOffset": 5527,
          "endOffset": 5937,
          "count": 1
        }
      ],
      "isBlockCoverage": true
    },
    {
      "functionName": "",
      "ranges": [
        {
          "startOffset": 5998,
          "endOffset": 6420,
          "count": 1
        }
      ],
      "isBlockCoverage": true
    },
    {
      "functionName": "",
      "ranges": [
        {
          "startOffset": 6061,
          "endOffset": 6416,
          "count": 1
        }
      ],
      "isBlockCoverage": true
    },
    {
      "functionName": "",
      "ranges": [
        {
          "startOffset": 6476,
          "endOffset": 6855,
          "count": 1
        }
      ],
      "isBlockCoverage": true
    },
    {
      "functionName": "",
      "ranges": [
        {
          "startOffset": 6537,
          "endOffset": 6851,
          "count": 1
        }
      ],
      "isBlockCoverage": true
    },
    {
      "functionName": "",
      "ranges": [
        {
          "startOffset": 6913,
          "endOffset": 7357,
          "count": 1
        }
      ],
      "isBlockCoverage": true
    },
    {
      "functionName": "",
      "ranges": [
        {
          "startOffset": 6976,
          "endOffset": 7353,
          "count": 1
        }
      ],
      "isBlockCoverage": true
    },
    {
      "functionName": "",
      "ranges": [
        {
          "startOffset": 7412,
          "endOffset": 7814,
          "count": 1
        }
      ],
      "isBlockCoverage": true
    },
    {
      "functionName": "",
      "ranges": [
        {
          "startOffset": 7472,
          "endOffset": 7810,
          "count": 1
        }
      ],
      "isBlockCoverage": true
    },
    {
      "functionName": "",
      "ranges": [
        {
          "startOffset": 7865,
          "endOffset": 8269,
          "count": 1
        }
      ],
      "isBlockCoverage": true
    },
    {
      "functionName": "",
      "ranges": [
        {
          "startOffset": 7921,
          "endOffset": 8265,
          "count": 1
        }
      ],
      "isBlockCoverage": true
    },
    {
      "functionName": "",
      "ranges": [
        {
          "startOffset": 8327,
          "endOffset": 8748,
          "count": 1
        }
      ],
      "isBlockCoverage": true
    },
    {
      "functionName": "",
      "ranges": [
        {
          "startOffset": 8391,
          "endOffset": 8744,
          "count": 1
        }
      ],
      "isBlockCoverage": true
    },
    {
      "functionName": "",
      "ranges": [
        {
          "startOffset": 8799,
          "endOffset": 9672,
          "count": 1
        }
      ],
      "isBlockCoverage": true
    },
    {
      "functionName": "",
      "ranges": [
        {
          "startOffset": 8859,
          "endOffset": 9243,
          "count": 1
        }
      ],
      "isBlockCoverage": true
    },
    {
      "functionName": "",
      "ranges": [
        {
          "startOffset": 9296,
          "endOffset": 9668,
          "count": 1
        }
      ],
      "isBlockCoverage": true
    },
    {
      "functionName": "",
      "ranges": [
        {
          "startOffset": 9718,
          "endOffset": 10707,
          "count": 1
        }
      ],
      "isBlockCoverage": true
    },
    {
      "functionName": "",
      "ranges": [
        {
          "startOffset": 9780,
          "endOffset": 9977,
          "count": 1
        }
      ],
      "isBlockCoverage": true
    },
    {
      "functionName": "",
      "ranges": [
        {
          "startOffset": 10029,
          "endOffset": 10315,
          "count": 1
        }
      ],
      "isBlockCoverage": true
    },
    {
      "functionName": "",
      "ranges": [
        {
          "startOffset": 10369,
          "endOffset": 10703,
          "count": 1
        }
      ],
      "isBlockCoverage": true
    },
    {
      "functionName": "",
      "ranges": [
        {
          "startOffset": 10792,
          "endOffset": 11263,
          "count": 1
        }
      ],
      "isBlockCoverage": true
    },
    {
      "functionName": "info",
      "ranges": [
        {
          "startOffset": 10854,
          "endOffset": 10860,
          "count": 0
        }
      ],
      "isBlockCoverage": false
    },
    {
      "functionName": "warn",
      "ranges": [
        {
          "startOffset": 10872,
          "endOffset": 10905,
          "count": 1
        }
      ],
      "isBlockCoverage": true
    },
    {
      "functionName": "error",
      "ranges": [
        {
          "startOffset": 10918,
          "endOffset": 10924,
          "count": 0
        }
      ],
      "isBlockCoverage": false
    },
    {
      "functionName": "writeDataPoint",
      "ranges": [
        {
          "startOffset": 10976,
          "endOffset": 11033,
          "count": 1
        }
      ],
      "isBlockCoverage": true
    }
  ]
}