{
  "scriptId": "335",
  "url": "file:///Users/jaysonknight/Projects/Code/adblock-compiler/src/configuration/schemas.test.ts",
  "functions": [
    {
      "functionName": "",
      "ranges": [
        {
          "startOffset": 0,
          "endOffset": 14233,
          "count": 1
        }
      ],
      "isBlockCoverage": true
    },
    {
      "functionName": "",
      "ranges": [
        {
          "startOffset": 571,
          "endOffset": 732,
          "count": 1
        }
      ],
      "isBlockCoverage": true
    },
    {
      "functionName": "",
      "ranges": [
        {
          "startOffset": 791,
          "endOffset": 1078,
          "count": 1
        }
      ],
      "isBlockCoverage": true
    },
    {
      "functionName": "",
      "ranges": [
        {
          "startOffset": 1143,
          "endOffset": 1277,
          "count": 1
        }
      ],
      "isBlockCoverage": true
    },
    {
      "functionName": "",
      "ranges": [
        {
          "startOffset": 1339,
          "endOffset": 1527,
          "count": 1
        }
      ],
      "isBlockCoverage": true
    },
    {
      "functionName": "",
      "ranges": [
        {
          "startOffset": 1632,
          "endOffset": 1866,
          "count": 1
        }
      ],
      "isBlockCoverage": true
    },
    {
      "functionName": "",
      "ranges": [
        {
          "startOffset": 1932,
          "endOffset": 2099,
          "count": 1
        }
      ],
      "isBlockCoverage": true
    },
    {
      "functionName": "",
      "ranges": [
        {
          "startOffset": 2192,
          "endOffset": 2461,
          "count": 1
        }
      ],
      "isBlockCoverage": true
    },
    {
      "functionName": "",
      "ranges": [
        {
          "startOffset": 2532,
          "endOffset": 2956,
          "count": 1
        }
      ],
      "isBlockCoverage": true
    },
    {
      "functionName": "",
      "ranges": [
        {
          "startOffset": 3067,
          "endOffset": 3622,
          "count": 1
        }
      ],
      "isBlockCoverage": true
    },
    {
      "functionName": "",
      "ranges": [
        {
          "startOffset": 3691,
          "endOffset": 4247,
          "count": 1
        }
      ],
      "isBlockCoverage": true
    },
    {
      "functionName": "",
      "ranges": [
        {
          "startOffset": 4324,
          "endOffset": 4714,
          "count": 1
        }
      ],
      "isBlockCoverage": true
    },
    {
      "functionName": "",
      "ranges": [
        {
          "startOffset": 4382,
          "endOffset": 4577,
          "count": 11
        }
      ],
      "isBlockCoverage": true
    },
    {
      "functionName": "",
      "ranges": [
        {
          "startOffset": 4781,
          "endOffset": 5170,
          "count": 1
        }
      ],
      "isBlockCoverage": true
    },
    {
      "functionName": "",
      "ranges": [
        {
          "startOffset": 4839,
          "endOffset": 5034,
          "count": 10
        }
      ],
      "isBlockCoverage": true
    },
    {
      "functionName": "",
      "ranges": [
        {
          "startOffset": 5282,
          "endOffset": 5674,
          "count": 1
        }
      ],
      "isBlockCoverage": true
    },
    {
      "functionName": "",
      "ranges": [
        {
          "startOffset": 5341,
          "endOffset": 5536,
          "count": 101
        }
      ],
      "isBlockCoverage": true
    },
    {
      "functionName": "",
      "ranges": [
        {
          "startOffset": 5743,
          "endOffset": 6134,
          "count": 1
        }
      ],
      "isBlockCoverage": true
    },
    {
      "functionName": "",
      "ranges": [
        {
          "startOffset": 5802,
          "endOffset": 5997,
          "count": 100
        }
      ],
      "isBlockCoverage": true
    },
    {
      "functionName": "",
      "ranges": [
        {
          "startOffset": 6206,
          "endOffset": 6580,
          "count": 1
        }
      ],
      "isBlockCoverage": true
    },
    {
      "functionName": "",
      "ranges": [
        {
          "startOffset": 6687,
          "endOffset": 6816,
          "count": 1
        }
      ],
      "isBlockCoverage": true
    },
    {
      "functionName": "",
      "ranges": [
        {
          "startOffset": 6888,
          "endOffset": 7188,
          "count": 1
        }
      ],
      "isBlockCoverage": true
    },
    {
      "functionName": "",
      "ranges": [
        {
          "startOffset": 7262,
          "endOffset": 7414,
          "count": 1
        }
      ],
      "isBlockCoverage": true
    },
    {
      "functionName": "",
      "ranges": [
        {
          "startOffset": 7491,
          "endOffset": 7644,
          "count": 1
        }
      ],
      "isBlockCoverage": true
    },
    {
      "functionName": "",
      "ranges": [
        {
          "startOffset": 7761,
          "endOffset": 7895,
          "count": 1
        }
      ],
      "isBlockCoverage": true
    },
    {
      "functionName": "",
      "ranges": [
        {
          "startOffset": 7992,
          "endOffset": 8227,
          "count": 1
        }
      ],
      "isBlockCoverage": true
    },
    {
      "functionName": "",
      "ranges": [
        {
          "startOffset": 8321,
          "endOffset": 8591,
          "count": 1
        }
      ],
      "isBlockCoverage": true
    },
    {
      "functionName": "",
      "ranges": [
        {
          "startOffset": 8672,
          "endOffset": 8893,
          "count": 1
        }
      ],
      "isBlockCoverage": true
    },
    {
      "functionName": "",
      "ranges": [
        {
          "startOffset": 8988,
          "endOffset": 9212,
          "count": 1
        }
      ],
      "isBlockCoverage": true
    },
    {
      "functionName": "fetch",
      "ranges": [
        {
          "startOffset": 9048,
          "endOffset": 9067,
          "count": 0
        }
      ],
      "isBlockCoverage": false
    },
    {
      "functionName": "canHandle",
      "ranges": [
        {
          "startOffset": 9086,
          "endOffset": 9094,
          "count": 0
        }
      ],
      "isBlockCoverage": false
    },
    {
      "functionName": "",
      "ranges": [
        {
          "startOffset": 9323,
          "endOffset": 9794,
          "count": 1
        },
        {
          "startOffset": 9643,
          "endOffset": 9792,
          "count": 10
        }
      ],
      "isBlockCoverage": true
    },
    {
      "functionName": "",
      "ranges": [
        {
          "startOffset": 9871,
          "endOffset": 9987,
          "count": 1
        }
      ],
      "isBlockCoverage": true
    },
    {
      "functionName": "",
      "ranges": [
        {
          "startOffset": 10100,
          "endOffset": 10365,
          "count": 1
        },
        {
          "startOffset": 10209,
          "endOffset": 10363,
          "count": 3
        }
      ],
      "isBlockCoverage": true
    },
    {
      "functionName": "",
      "ranges": [
        {
          "startOffset": 10439,
          "endOffset": 10550,
          "count": 1
        }
      ],
      "isBlockCoverage": true
    },
    {
      "functionName": "",
      "ranges": [
        {
          "startOffset": 10651,
          "endOffset": 10892,
          "count": 1
        }
      ],
      "isBlockCoverage": true
    },
    {
      "functionName": "",
      "ranges": [
        {
          "startOffset": 10959,
          "endOffset": 11361,
          "count": 1
        }
      ],
      "isBlockCoverage": true
    },
    {
      "functionName": "",
      "ranges": [
        {
          "startOffset": 11435,
          "endOffset": 11687,
          "count": 1
        }
      ],
      "isBlockCoverage": true
    },
    {
      "functionName": "",
      "ranges": [
        {
          "startOffset": 11789,
          "endOffset": 12053,
          "count": 1
        }
      ],
      "isBlockCoverage": true
    },
    {
      "functionName": "",
      "ranges": [
        {
          "startOffset": 12129,
          "endOffset": 12846,
          "count": 1
        }
      ],
      "isBlockCoverage": true
    },
    {
      "functionName": "",
      "ranges": [
        {
          "startOffset": 12917,
          "endOffset": 13183,
          "count": 1
        }
      ],
      "isBlockCoverage": true
    },
    {
      "functionName": "",
      "ranges": [
        {
          "startOffset": 13296,
          "endOffset": 13619,
          "count": 1
        }
      ],
      "isBlockCoverage": true
    },
    {
      "functionName": "",
      "ranges": [
        {
          "startOffset": 13705,
          "endOffset": 14230,
          "count": 1
        }
      ],
      "isBlockCoverage": true
    }
  ]
}